parallels_plugin/__init__.py
parallels_plugin/login.py
parallels_plugin/parallels_backend.py
parallels_plugin/parallels_core.py
parallels_plugin/infinfs/__init__.py
parallels_plugin/infinfs/infin_download.py
parallels_plugin/infinfs/infin_prefetch.py
parallels_plugin/infinfs/infinfs.py
parallels_plugin/infinfs/infinmount.py
parallels_plugin-0.3.6.dist-info/METADATA
parallels_plugin-0.3.6.dist-info/WHEEL
parallels_plugin-0.3.6.dist-info/entry_points.txt
parallels_plugin-0.3.6.dist-info/top_level.txt
parallels_plugin-0.3.6.dist-info/RECORD
