Metadata-Version: 2.1
Name: parallels-plugin
Version: 0.3.6
Summary: Plugin for MLflow Parallels
Home-page: UNKNOWN
Author: UNKNOWN
Author-email: UNKNOWN
License: UNKNOWN
Platform: UNKNOWN
Requires-Dist: mlflow (>=1.21.0)
Requires-Dist: jsons
Requires-Dist: kubernetes
